casa_fits/Image.py
casa_fits/__init__.py
casa_fits/azimuth_cut.py
casa_fits/detectpeak.py
casa_fits/imshow.py
casa_fits/imstat.py
casa_fits/io.py
casa_fits/matplotlib_helper.py
casa_fits/radial_cut.py
casa_fits/radial_profile.py
casa_fits/utilities.py
casa_fits-1.0.3.dist-info/METADATA
casa_fits-1.0.3.dist-info/WHEEL
casa_fits-1.0.3.dist-info/top_level.txt
casa_fits-1.0.3.dist-info/RECORD
