Metadata-Version: 2.4
Name: casa-fits
Version: 1.0.3
Summary: A collection of image scripts supporting both FITS and CASA image formats.
License: MIT
Requires-Python: >=3.11
Requires-Dist: astropy>=7.1.0
Requires-Dist: casatasks>=6.6.1
Requires-Dist: casatools>=6.6.1
Requires-Dist: matplotlib>=3.10.0
Requires-Dist: numpy>=2.2.3
Requires-Dist: pyqt5>=5.15.11
Requires-Dist: scipy>=1.15.1
